Metadata-Version: 1.0
Name: sicca-distributions
Version: 1.0
Summary: Gaussian and Binomial distributions
Home-page: UNKNOWN
Author: Eduardo Siqueira
Author-email: eduardochagasds@gmail.com
License: UNKNOWN
Platform: UNKNOWN
